CHANGELOG.txt
LICENCE.txt
MANIFEST.in
README.txt
setup.py
amritdummycalculator/__init__.py
democal1.egg-info/PKG-INFO
democal1.egg-info/SOURCES.txt
democal1.egg-info/dependency_links.txt
democal1.egg-info/top_level.txt