Metadata-Version: 1.1
Name: democal1
Version: 0.0.2
Summary: dummycalci1
Home-page: UNKNOWN
Author: amrit250
Author-email: amrit.gaur549@gmail.com
License: MIT
Keywords: speedtest
Platform: UNKNOWN
Classifier: Development Status :: 5 - Production/Stable
Classifier: Intended Audience :: Education
Classifier: Operating System :: Microsoft :: Windows :: Windows 10
Classifier: License :: OSI Approved :: MIT License
Classifier: Programming Language :: Python :: 3.8
